km_plugin_ecm
