Metadata-Version: 2.1
Name: km-plugin-ecm
Version: 1.2
Summary: 知识管理系统插件-洪翼系统对接
Author: KnowledgeManagement
Requires-Dist: km-sdk>=1.0.1
Requires-Dist: requests
